kuunda/__init__.py
kuunda-0.0.1.dist-info/METADATA
kuunda-0.0.1.dist-info/WHEEL
kuunda-0.0.1.dist-info/RECORD
